PythonStackTracer/__init__.py
robotframework_pythonstacktrace-0.1.1.dist-info/LICENSE
robotframework_pythonstacktrace-0.1.1.dist-info/WHEEL
robotframework_pythonstacktrace-0.1.1.dist-info/METADATA
robotframework_pythonstacktrace-0.1.1.dist-info/RECORD
