Metadata-Version: 2.1
Name: robotframework-pythonstacktrace
Version: 0.1.1
Summary: Robot Framework listener that prints Python traceback for failing keywords.
Home-page: https://github.com/aajn/robotframework-pythonstacktrace
License: Apache-2.0
Author: Piotr Chromiński
Author-email: piot.chrom@gmail.com
Requires-Python: >=3.7,<4.0
Classifier: Framework :: Robot Framework
Classifier: License :: OSI Approved :: Apache Software License
Classifier: Operating System :: OS Independent
Classifier: Programming Language :: Python :: 3
Classifier: Programming Language :: Python :: 3.10
Classifier: Programming Language :: Python :: 3.7
Classifier: Programming Language :: Python :: 3.8
Classifier: Programming Language :: Python :: 3.9
Classifier: Topic :: Software Development :: Testing
Classifier: Topic :: Software Development :: Testing :: Acceptance
Requires-Dist: robotframework (>=5)
Requires-Dist: robotframework-tidy (>=2.3,<3.0)
Project-URL: Repository, https://github.com/aajn/robotframework-pythonstacktrace
